cdh_main.py
cdh_main-2.0.5.dist-info/WHEEL
cdh_main-2.0.5.dist-info/METADATA
cdh_main-2.0.5.dist-info/RECORD
