Metadata-Version: 2.1
Name: cdh-main
Version: 2.0.5
Summary: Three folded data structure {(ID) key : value} with ID as int, key as str and value as variable type
License: Free to use
Author: Roberto Amadori
Author-email: robiamado@gmail.com
Classifier: License :: Other/Proprietary License
Classifier: Programming Language :: Python :: 2
Classifier: Programming Language :: Python :: 2.7
Classifier: Programming Language :: Python :: 3
Classifier: Programming Language :: Python :: 3.4
Classifier: Programming Language :: Python :: 3.5
Classifier: Programming Language :: Python :: 3.6
Classifier: Programming Language :: Python :: 3.7
Classifier: Programming Language :: Python :: 3.8
Classifier: Programming Language :: Python :: 3.9
